{
  "openapi": "3.0.4",
  "info": {
    "title": "My API",
    "version": "v1"
  },
  "paths": {
    "/api/Company": {
      "get": {
        "tags": [
          "Company"
        ],
        "responses": {
          "200": {
            "description": "OK",
            "content": {
              "text/plain": {
                "schema": {
                  "$ref": "#/components/schemas/CompanyReadDto"
                }
              },
              "application/json": {
                "schema": {
                  "$ref": "#/components/schemas/CompanyReadDto"
                }
              },
              "text/json": {
                "schema": {
                  "$ref": "#/components/schemas/CompanyReadDto"
                }
              }
            }
          }
        }
      },
      "post": {
        "tags": [
          "Company"
        ],
        "requestBody": {
          "content": {
            "application/json": {
              "schema": {
                "$ref": "#/components/schemas/CompanyCreateDto"
              }
            },
            "text/json": {
              "schema": {
                "$ref": "#/components/schemas/CompanyCreateDto"
              }
            },
            "application/*+json": {
              "schema": {
                "$ref": "#/components/schemas/CompanyCreateDto"
              }
            }
          }
        },
        "responses": {
          "200": {
            "description": "OK",
            "content": {
              "text/plain": {
                "schema": {
                  "$ref": "#/components/schemas/CompanyCreateDto"
                }
              },
              "application/json": {
                "schema": {
                  "$ref": "#/components/schemas/CompanyCreateDto"
                }
              },
              "text/json": {
                "schema": {
                  "$ref": "#/components/schemas/CompanyCreateDto"
                }
              }
            }
          }
        }
      },
      "put": {
        "tags": [
          "Company"
        ],
        "requestBody": {
          "content": {
            "application/json": {
              "schema": {
                "$ref": "#/components/schemas/CompanyUpdateDto"
              }
            },
            "text/json": {
              "schema": {
                "$ref": "#/components/schemas/CompanyUpdateDto"
              }
            },
            "application/*+json": {
              "schema": {
                "$ref": "#/components/schemas/CompanyUpdateDto"
              }
            }
          }
        },
        "responses": {
          "200": {
            "description": "OK",
            "content": {
              "text/plain": {
                "schema": {
                  "$ref": "#/components/schemas/CompanyUpdateDto"
                }
              },
              "application/json": {
                "schema": {
                  "$ref": "#/components/schemas/CompanyUpdateDto"
                }
              },
              "text/json": {
                "schema": {
                  "$ref": "#/components/schemas/CompanyUpdateDto"
                }
              }
            }
          }
        }
      }
    },
    "/api/Company/{id}": {
      "get": {
        "tags": [
          "Company"
        ],
        "parameters": [
          {
            "name": "id",
            "in": "path",
            "required": true,
            "schema": {
              "type": "integer",
              "format": "int32"
            }
          }
        ],
        "responses": {
          "200": {
            "description": "OK",
            "content": {
              "text/plain": {
                "schema": {
                  "$ref": "#/components/schemas/CompanyReadDto"
                }
              },
              "application/json": {
                "schema": {
                  "$ref": "#/components/schemas/CompanyReadDto"
                }
              },
              "text/json": {
                "schema": {
                  "$ref": "#/components/schemas/CompanyReadDto"
                }
              }
            }
          }
        }
      },
      "delete": {
        "tags": [
          "Company"
        ],
        "parameters": [
          {
            "name": "id",
            "in": "path",
            "required": true,
            "schema": {
              "type": "integer",
              "format": "int32"
            }
          }
        ],
        "responses": {
          "200": {
            "description": "OK",
            "content": {
              "text/plain": {
                "schema": {
                  "$ref": "#/components/schemas/CompanyReadDto"
                }
              },
              "application/json": {
                "schema": {
                  "$ref": "#/components/schemas/CompanyReadDto"
                }
              },
              "text/json": {
                "schema": {
                  "$ref": "#/components/schemas/CompanyReadDto"
                }
              }
            }
          }
        }
      }
    },
    "/api/Company/companies-with-departments": {
      "get": {
        "tags": [
          "Company"
        ],
        "responses": {
          "200": {
            "description": "OK"
          }
        }
      }
    },
    "/WeatherForecast": {
      "get": {
        "tags": [
          "WeatherForecast"
        ],
        "operationId": "GetWeatherForecast",
        "responses": {
          "200": {
            "description": "OK",
            "content": {
              "text/plain": {
                "schema": {
                  "type": "array",
                  "items": {
                    "$ref": "#/components/schemas/WeatherForecast"
                  }
                }
              },
              "application/json": {
                "schema": {
                  "type": "array",
                  "items": {
                    "$ref": "#/components/schemas/WeatherForecast"
                  }
                }
              },
              "text/json": {
                "schema": {
                  "type": "array",
                  "items": {
                    "$ref": "#/components/schemas/WeatherForecast"
                  }
                }
              }
            }
          }
        }
      }
    }
  },
  "components": {
    "schemas": {
      "CompanyCreateDto": {
        "type": "object",
        "properties": {
          "name": {
            "type": "string",
            "nullable": true
          },
          "address": {
            "type": "string",
            "nullable": true
          },
          "country": {
            "type": "string",
            "nullable": true
          }
        },
        "additionalProperties": false
      },
      "CompanyReadDto": {
        "type": "object",
        "properties": {
          "id": {
            "type": "integer",
            "format": "int32"
          },
          "name": {
            "type": "string",
            "nullable": true
          },
          "country": {
            "type": "string",
            "nullable": true
          },
          "departments": {
            "type": "array",
            "items": {
              "$ref": "#/components/schemas/DepartmentDto"
            },
            "nullable": true
          }
        },
        "additionalProperties": false
      },
      "CompanyUpdateDto": {
        "type": "object",
        "properties": {
          "id": {
            "type": "integer",
            "format": "int32"
          },
          "name": {
            "type": "string",
            "nullable": true
          },
          "address": {
            "type": "string",
            "nullable": true
          },
          "country": {
            "type": "string",
            "nullable": true
          }
        },
        "additionalProperties": false
      },
      "DepartmentDto": {
        "type": "object",
        "properties": {
          "id": {
            "type": "integer",
            "format": "int32"
          },
          "companyId": {
            "type": "integer",
            "format": "int32"
          },
          "name": {
            "type": "string",
            "nullable": true
          },
          "description": {
            "type": "string",
            "nullable": true
          }
        },
        "additionalProperties": false
      },
      "WeatherForecast": {
        "type": "object",
        "properties": {
          "date": {
            "type": "string",
            "format": "date"
          },
          "temperatureC": {
            "type": "integer",
            "format": "int32"
          },
          "temperatureF": {
            "type": "integer",
            "format": "int32",
            "readOnly": true
          },
          "summary": {
            "type": "string",
            "nullable": true
          }
        },
        "additionalProperties": false
      }
    }
  },
  "tags": [
    {
      "name": "Company"
    },
    {
      "name": "WeatherForecast"
    }
  ]
}